juicenet/__init__.py
juicenet/__main__.py
juicenet/bar.py
juicenet/cli.py
juicenet/compat.py
juicenet/config.py
juicenet/exceptions.py
juicenet/log.py
juicenet/main.py
juicenet/model.py
juicenet/nyuu.py
juicenet/parpar.py
juicenet/py.typed
juicenet/resume.py
juicenet/types.py
juicenet/utils.py
juicenet/version.py
juicenet/api/__init__.py
juicenet/api/main.py
juicenet/api/utils.py
juicenet_cli-0.47.0.dist-info/METADATA
juicenet_cli-0.47.0.dist-info/WHEEL
juicenet_cli-0.47.0.dist-info/entry_points.txt
juicenet_cli-0.47.0.dist-info/RECORD
