Metadata-Version: 2.4
Name: juicenet-cli
Version: 0.47.0
Summary: CLI tool designed to simplify the process of uploading files to Usenet
Project-URL: Repository, https://github.com/Ravencentric/juicenet-cli
Project-URL: Documentation, https://juicenet.ravencentric.cc
Author-email: Ravencentric <me@ravencentric.cc>
License-Expression: Unlicense
Classifier: License :: OSI Approved :: The Unlicense (Unlicense)
Classifier: Operating System :: OS Independent
Classifier: Programming Language :: Python :: 3.9
Classifier: Programming Language :: Python :: 3.10
Classifier: Programming Language :: Python :: 3.11
Classifier: Programming Language :: Python :: 3.12
Classifier: Programming Language :: Python :: 3.13
Classifier: Typing :: Typed
Requires-Python: >=3.9
Requires-Dist: colorama>=0.4.6
Requires-Dist: cyclopts>=2.9.3
Requires-Dist: importlib-metadata>=8.0.0; python_version < '3.10'
Requires-Dist: loguru>=0.7.2
Requires-Dist: natsort>=8.4.0
Requires-Dist: pydantic>=2.8.2
Requires-Dist: pyyaml>=6.0.1
Requires-Dist: rich>=13.7.1
Requires-Dist: strenum>=0.4.15; python_version < '3.11'
